.gitignore
.travis.yml
MANIFEST.in
README.rst
bootstrap.py
setup.py
travis.cfg
docs/HISTORY.txt
docs/INSTALL.txt
docs/LICENSE.GPL
docs/LICENSE.txt
src/collective/__init__.py
src/collective.geo.mapwidget.egg-info/PKG-INFO
src/collective.geo.mapwidget.egg-info/SOURCES.txt
src/collective.geo.mapwidget.egg-info/dependency_links.txt
src/collective.geo.mapwidget.egg-info/entry_points.txt
src/collective.geo.mapwidget.egg-info/namespace_packages.txt
src/collective.geo.mapwidget.egg-info/not-zip-safe
src/collective.geo.mapwidget.egg-info/requires.txt
src/collective.geo.mapwidget.egg-info/top_level.txt
src/collective/geo/__init__.py
src/collective/geo/mapwidget/README.txt
src/collective/geo/mapwidget/__init__.py
src/collective/geo/mapwidget/config.py
src/collective/geo/mapwidget/configure.zcml
src/collective/geo/mapwidget/indexer.py
src/collective/geo/mapwidget/interfaces.py
src/collective/geo/mapwidget/maplayers.py
src/collective/geo/mapwidget/maplayers.zcml
src/collective/geo/mapwidget/profiles.zcml
src/collective/geo/mapwidget/testing.py
src/collective/geo/mapwidget/testing.zcml
src/collective/geo/mapwidget/upgrades.py
src/collective/geo/mapwidget/utils.py
src/collective/geo/mapwidget/vocabularies.py
src/collective/geo/mapwidget/browser/__init__.py
src/collective/geo/mapwidget/browser/collectivegeo_macros.pt
src/collective/geo/mapwidget/browser/collectivegeo_macros.py
src/collective/geo/mapwidget/browser/configure.zcml
src/collective/geo/mapwidget/browser/controlpanel.pt
src/collective/geo/mapwidget/browser/controlpanel.py
src/collective/geo/mapwidget/browser/controlpanel.txt
src/collective/geo/mapwidget/browser/form-with-subforms.pt
src/collective/geo/mapwidget/browser/geocoder.py
src/collective/geo/mapwidget/browser/geofeaturestyle_view.py
src/collective/geo/mapwidget/browser/geopointform.pt
src/collective/geo/mapwidget/browser/geosettings_view.py
src/collective/geo/mapwidget/browser/interfaces.py
src/collective/geo/mapwidget/browser/shapewidget.py
src/collective/geo/mapwidget/browser/widget.py
src/collective/geo/mapwidget/browser/layers_templates/bing_aer_layer.pt
src/collective/geo/mapwidget/browser/layers_templates/bing_hyb_layer.pt
src/collective/geo/mapwidget/browser/layers_templates/bing_map_layer.pt
src/collective/geo/mapwidget/browser/layers_templates/bing_rod_layer.pt
src/collective/geo/mapwidget/browser/layers_templates/google_hyb_layer.pt
